flask_fs_router/__init__.py
flask_fs_router-1.1.2.dist-info/LICENSE
flask_fs_router-1.1.2.dist-info/METADATA
flask_fs_router-1.1.2.dist-info/WHEEL
flask_fs_router-1.1.2.dist-info/top_level.txt
flask_fs_router-1.1.2.dist-info/RECORD
