Metadata-Version: 2.1
Name: flask-fs-router
Version: 1.1.2
Summary: Straightforward file-based routing extension for Flask. Introduces the concepts of pages to Flask.
Home-page: https://github.com/JarriqTheTechie/flask_fs_router
Author: Jarriq Rolle
Author-email: jrolle@bnbbahamas.com
License: MIT license
Keywords: Python,Development,Flask
Classifier: Development Status :: 5 - Production/Stable
Classifier: Intended Audience :: Developers
Classifier: Environment :: Web Environment
Classifier: License :: OSI Approved :: MIT License
Classifier: Operating System :: OS Independent
Classifier: Programming Language :: Python :: 3.6
Classifier: Programming Language :: Python :: 3.7
Classifier: Programming Language :: Python :: 3.8
Classifier: Programming Language :: Python :: 3.9
Classifier: Topic :: Software Development :: Libraries :: Application Frameworks
Classifier: Topic :: Software Development :: Libraries :: Python Modules
Classifier: Framework :: Flask
License-File: LICENSE
